rt_pose/__init__.py
rt_pose/pipeline.py
rt_pose/processing.py
rt_pose-0.0.3.dist-info/METADATA
rt_pose-0.0.3.dist-info/WHEEL
rt_pose-0.0.3.dist-info/licenses/LICENSE
rt_pose-0.0.3.dist-info/RECORD
