Metadata-Version: 2.4
Name: rt-pose
Version: 0.0.3
Summary: Real-time (GPU) pose estimation pipeline with 🤗 Transformers
Author-email: Pavel Iakubovskii <qubvel@gmail.com>
License-File: LICENSE
Requires-Python: >=3.8
Requires-Dist: loguru
Requires-Dist: numpy
Requires-Dist: torch>=2.1.0
Requires-Dist: torchvision
Requires-Dist: transformers[vision]>=4.48.0
Provides-Extra: demo
Requires-Dist: moviepy>=2.1.1; extra == 'demo'
Requires-Dist: pillow; extra == 'demo'
Requires-Dist: requests; extra == 'demo'
Requires-Dist: supervision>=0.25.0; extra == 'demo'
Requires-Dist: tqdm; extra == 'demo'
Provides-Extra: dev
Requires-Dist: pytest; extra == 'dev'
Requires-Dist: ruff; extra == 'dev'
